fsrs4anki_optimizer/__init__.py
fsrs4anki_optimizer/__main__.py
fsrs4anki_optimizer/fsrs4anki_optimizer.py
fsrs4anki_optimizer-4.4.1.dist-info/METADATA
fsrs4anki_optimizer-4.4.1.dist-info/WHEEL
fsrs4anki_optimizer-4.4.1.dist-info/top_level.txt
fsrs4anki_optimizer-4.4.1.dist-info/RECORD
