Metadata-Version: 2.1
Name: fsrs4anki-optimizer
Version: 4.4.1
Project-URL: Homepage, https://github.com/open-spaced-repetition/fsrs4anki
Requires-Python: >=3.8
Requires-Dist: matplotlib (>=3.7.0)
Requires-Dist: numpy (>=1.22.4)
Requires-Dist: pandas (>=1.5.3)
Requires-Dist: pytz (>=2022.7.1)
Requires-Dist: scikit-learn (>=1.2.2)
Requires-Dist: torch (>=1.13.1)
Requires-Dist: tqdm (>=4.64.1)
Requires-Dist: statsmodels (>=0.13.5)
